.project
.pydevproject
ez_setup.py
setup.cfg
setup.py
Scripts/find_nowandnext.py
examples/tagtest.py
src/__init__.py
src/nowandnext/Mp3Maker.py
src/nowandnext/__init__.py
src/nowandnext/id3frameadaptor.py
src/nowandnext/listenagain.py
src/nowandnext/parkup.py
src/nowandnext/simplecast.py
src/nowandnext.egg-info/PKG-INFO
src/nowandnext.egg-info/SOURCES.txt
src/nowandnext.egg-info/dependency_links.txt
src/nowandnext.egg-info/entry_points.txt
src/nowandnext.egg-info/requires.txt
src/nowandnext.egg-info/top_level.txt
src/nowandnext.egg-info/zip-safe
src/nowandnext/applications/__init__.py
src/nowandnext/applications/emulate_simplecast.py
src/nowandnext/applications/itunes_gateway.py
src/nowandnext/applications/metapod.py
src/nowandnext/applications/pinger.py
src/nowandnext/applications/schedule_to_digiguide.py
src/nowandnext/applications/schedule_to_errors.py
src/nowandnext/applications/schedule_to_rss.py
src/nowandnext/archivedotorg/__init__.py
src/nowandnext/archivedotorg/archiveorgadaptor.py
src/nowandnext/calendar/__init__.py
src/nowandnext/calendar/calQuery.py
src/nowandnext/calendar/convert.py
src/nowandnext/calendar/detecterrorsinevent.py
src/nowandnext/calendar/gdate.py
src/nowandnext/calendar/gevent.py
src/nowandnext/calendar/geventinstance.py
src/nowandnext/calendar/periods.py
src/nowandnext/calendar/scheduleevent.py
src/nowandnext/calendar/schedulegap.py
src/nowandnext/calendar/schedulething.py
src/nowandnext/digiguide/__init__.py
src/nowandnext/digiguide/categories.py
src/nowandnext/digiguide/dgpublish.py
src/nowandnext/digiguide/dgxml.py
src/nowandnext/gateway/__init__.py
src/nowandnext/gateway/gatewayhandler.py
src/nowandnext/tests/__init__.py
src/nowandnext/tests/test_basic.py
src/nowandnext/tests/test_event_instances.py
src/nowandnext/tests/test_events.py
src/nowandnext/tests/test_schedule_items.py
src/nowandnext/timezones/FixedOffset.py
src/nowandnext/timezones/__init__.py
src/nowandnext/timezones/uk.py
src/nowandnext/timezones/utc.py
src/nowandnext/utils/__init__.py
src/nowandnext/utils/cmdline.py
src/nowandnext/utils/detectos.py
src/nowandnext/utils/textparser.py
src/nowandnext/utils/data/resonance_archiver.cfg.example
src/nowandnext/utils/data/resonance_listenagain.cfg.example
