Metadata-Version: 1.0
Name: nowandnext
Version: 0.2.5.dev-r493
Summary: A SimpleCast compatible metadata generation tool for radio stations who use Google Calendar to design and publish their broadcast schedule.
Home-page: http://code.google.com/p/suxtools/
Author: Salim Fadhley
Author-email: sal@stodge.org
License: GPL
Keywords: google calendar query
Platform: UNKNOWN
